ed_webhook/__init__.py
ed_webhook/application/__init__.py
ed_webhook/application/common/__init__.py
ed_webhook/application/common/responses/__init__.py
ed_webhook/application/common/responses/base_response.py
ed_webhook/application/contracts/__init__.py
ed_webhook/application/features/__init__.py
ed_webhook/application/features/common/__init__.py
ed_webhook/application/features/common/dto/__init__.py
ed_webhook/application/features/webhook/__init__.py
ed_webhook/application/features/webhook/dtos/__init__.py
ed_webhook/application/features/webhook/dtos/validators/__init__.py
ed_webhook/application/features/webhook/handlers/__init__.py
ed_webhook/application/features/webhook/handlers/commands/__init__.py
ed_webhook/application/features/webhook/handlers/commands/send_webhook_command_handler.py
ed_webhook/application/features/webhook/handlers/queries/__init__.py
ed_webhook/application/features/webhook/requests/__init__.py
ed_webhook/application/features/webhook/requests/commands/__init__.py
ed_webhook/application/features/webhook/requests/commands/send_webhook_command.py
ed_webhook/application/features/webhook/requests/queries/__init__.py
ed_webhook/application/services/__init__.py
ed_webhook/application/services/abc_service.py
ed_webhook/common/__init__.py
ed_webhook/common/exception_helpers.py
ed_webhook/common/generic_helpers.py
ed_webhook/common/logging_helpers.py
ed_webhook/common/singleton_helpers.py
ed_webhook/common/typing/__init__.py
ed_webhook/common/typing/config.py
ed_webhook/documentation/__init__.py
ed_webhook/documentation/api/__init__.py
ed_webhook/documentation/api/abc_webhook_api_client.py
ed_webhook/documentation/api/webhook_api_client.py
ed_webhook/documentation/api/webhook_endpoint_descriptions.py
ed_webhook/infrastructure/__init__.py
ed_webhook/webapi/__init__.py
ed_webhook/webapi/api.py
ed_webhook/webapi/dependency_setup.py
ed_webhook/webapi/common/__init__.py
ed_webhook/webapi/common/helpers.py
ed_webhook/webapi/controllers/__init__.py
ed_webhook_service-0.1.9.dist-info/licenses/LICENSE
ed_webhook_service-0.1.9.dist-info/METADATA
ed_webhook_service-0.1.9.dist-info/WHEEL
ed_webhook_service-0.1.9.dist-info/top_level.txt
ed_webhook_service-0.1.9.dist-info/RECORD
