Metadata-Version: 2.4
Name: ed_webhook_service
Version: 0.1.9
Summary: EasyDrop auth model Package
Home-page: https://github.com/ffekirnew/ed-webhook
Author: Fikernew Birhanu
Author-email: fikernew.birhanu.waju@gmail.com
Project-URL: Documentation, https://github.com/easydropet/ed-webhook
Project-URL: Bug Reports, https://github.com/easydropet/ed-webhook/issues
Project-URL: Source Code, https://github.com/easydropet/ed-webhook
Keywords: ed_webhook,pypi,package
Classifier: Development Status :: 5 - Production/Stable
Classifier: Intended Audience :: Developers
Classifier: Topic :: Software Development :: Build Tools
Classifier: Programming Language :: Python :: 3
Classifier: Programming Language :: Python :: 3.11
Classifier: Programming Language :: Python :: 3 :: Only
Classifier: License :: OSI Approved :: MIT License
Classifier: Operating System :: OS Independent
Requires-Python: >=3.12
License-File: LICENSE
Provides-Extra: dev
Requires-Dist: check-manifest; extra == "dev"
Dynamic: author
Dynamic: author-email
Dynamic: classifier
Dynamic: description
Dynamic: description-content-type
Dynamic: home-page
Dynamic: keywords
Dynamic: license-file
Dynamic: project-url
Dynamic: provides-extra
Dynamic: requires-python
Dynamic: summary
